.bzrignore
.gitignore
.travis.yml
CHANGES.rst
COPYRIGHT.txt
LICENSE.txt
README.rst
setup.cfg
setup.py
tox.ini
appendonly/__init__.py
appendonly/interfaces.py
appendonly/tests.py
appendonly.egg-info/PKG-INFO
appendonly.egg-info/SOURCES.txt
appendonly.egg-info/dependency_links.txt
appendonly.egg-info/not-zip-safe
appendonly.egg-info/requires.txt
appendonly.egg-info/top_level.txt